dataquality/__init__.py
dataquality/analytics.py
dataquality/clients/__init__.py
dataquality/clients/api.py
dataquality/clients/objectstore.py
dataquality/core/__init__.py
dataquality/core/_config.py
dataquality/core/auth.py
dataquality/core/finish.py
dataquality/core/init.py
dataquality/core/log.py
dataquality/core/report.py
dataquality/dq_auto/__init__.py
dataquality/dq_auto/auto.py
dataquality/dq_auto/base_data_manager.py
dataquality/dq_auto/ner.py
dataquality/dq_auto/ner_trainer.py
dataquality/dq_auto/notebook.py
dataquality/dq_auto/schema.py
dataquality/dq_auto/tc_trainer.py
dataquality/dq_auto/text_classification.py
dataquality/dq_start/__init__.py
dataquality/dqyolo.py
dataquality/exceptions.py
dataquality/integrations/__init__.py
dataquality/integrations/fastai.py
dataquality/integrations/hf.py
dataquality/integrations/jsl.py
dataquality/integrations/keras.py
dataquality/integrations/legacy/keras.py
dataquality/integrations/lightning.py
dataquality/integrations/seq2seq/__init__.py
dataquality/integrations/seq2seq/auto.py
dataquality/integrations/seq2seq/core.py
dataquality/integrations/seq2seq/formatters/__init__.py
dataquality/integrations/seq2seq/formatters/alpaca.py
dataquality/integrations/seq2seq/formatters/base.py
dataquality/integrations/seq2seq/formatters/chat.py
dataquality/integrations/seq2seq/s2s_trainer.py
dataquality/integrations/seq2seq/schema.py
dataquality/integrations/setfit.py
dataquality/integrations/torch.py
dataquality/integrations/torch_semantic_segmentation.py
dataquality/integrations/transformers_trainer.py
dataquality/integrations/ultralytics.py
dataquality/internal.py
dataquality/loggers/__init__.py
dataquality/loggers/base_logger.py
dataquality/loggers/data_logger/__init__.py
dataquality/loggers/data_logger/base_data_logger.py
dataquality/loggers/data_logger/image_classification.py
dataquality/loggers/data_logger/object_detection.py
dataquality/loggers/data_logger/semantic_segmentation.py
dataquality-2.3.0.dist-info/LICENSE
dataquality-2.3.0.dist-info/METADATA
dataquality-2.3.0.dist-info/WHEEL
dataquality-2.3.0.dist-info/entry_points.txt
dataquality-2.3.0.dist-info/RECORD
