Metadata-Version: 2.1
Name: dataquality
Version: 2.3.0
Summary: 
Home-page: https://github.com/rungalileo/dataquality
License: Apache-2.0
Author: Galileo Technologies, Inc.
Author-email: team@rungalileo.io
Requires-Python: >=3.9,<3.11
Classifier: License :: OSI Approved :: Apache Software License
Classifier: Programming Language :: Python :: 3
Classifier: Programming Language :: Python :: 3.9
Classifier: Programming Language :: Python :: 3.10
Provides-Extra: cuda
Provides-Extra: cuda11
Provides-Extra: cuda12
Provides-Extra: cv
Provides-Extra: minio
Provides-Extra: setfit
Requires-Dist: Pillow ; extra == "cv"
Requires-Dist: accelerate
Requires-Dist: blake3 (>=0.2.1)
Requires-Dist: cachetools (>=4.2.4)
Requires-Dist: cudf-cu12 (==24.2.0) ; extra == "cuda" or extra == "cuda12"
Requires-Dist: cuml-cu12 (==24.2.0) ; extra == "cuda" or extra == "cuda12"
Requires-Dist: dask-cudf-cu12 (==24.2.0) ; extra == "cuda" or extra == "cuda12"
Requires-Dist: datasets (>=2.14.6)
Requires-Dist: diskcache (>=5.2.1)
Requires-Dist: evaluate
Requires-Dist: h5py (>=3.1.0)
Requires-Dist: imagededup (>=0.3.1,<0.3.2) ; extra == "cv"
Requires-Dist: importlib-metadata (<6.0.1)
Requires-Dist: ipywidgets (>=8.1.0)
Requires-Dist: minio (>=7.1.0,<7.2.0) ; extra == "minio"
Requires-Dist: numpy (<1.24.0)
Requires-Dist: opencv-python (<=4.8.1.78) ; extra == "cv"
Requires-Dist: pandas (>=0.20.0)
Requires-Dist: peft
Requires-Dist: pyarrow (>=5.0.0)
Requires-Dist: pydantic (>=2.0.0)
Requires-Dist: pydantic-settings (>=2.0.0)
Requires-Dist: pyjwt (>=2.8.0)
Requires-Dist: pylibraft-cu12 (==24.2.0) ; extra == "cuda" or extra == "cuda12"
Requires-Dist: raft-dask-cu12 (==24.2.0) ; extra == "cuda" or extra == "cuda12"
Requires-Dist: requests (>=2.25.1)
Requires-Dist: resource (>=0.2.1)
Requires-Dist: rmm-cu12 (==24.2.0) ; extra == "cuda" or extra == "cuda12"
Requires-Dist: scipy (>=1.7.0)
Requires-Dist: sentence-transformers (>=2.2)
Requires-Dist: sentencepiece (>=0.2.0,<0.3.0)
Requires-Dist: seqeval
Requires-Dist: setfit (==0.7.0) ; extra == "setfit"
Requires-Dist: tenacity (>=8.1.0)
Requires-Dist: tensorflow (>=2.9.1,<2.15.0)
Requires-Dist: tqdm (>=4.62.3)
Requires-Dist: transformers (>=4.17.0)
Requires-Dist: ucx-py-cu12 (==0.36) ; extra == "cuda" or extra == "cuda12"
Requires-Dist: vaex-core (==4.17.1)
Requires-Dist: vaex-hdf5 (>=0.12,<0.13)
Requires-Dist: wrapt (>=1.13.3)
Project-URL: Documentation, https://rungalileo.gitbook.io/galileo
